{
  "metadata": {
    "totalPatterns": 4,
    "providers": [
      "bun_official",
      "mdn_web_docs",
      "github",
      "cloudflare",
      "vercel",
      "performance_guides"
    ],
    "categories": [
      "cookies",
      "r2",
      "s3-presign",
      "performance"
    ],
    "tags": [
      "ab-testing",
      "variant",
      "cookie",
      "ui",
      "admin",
      "http",
      "header",
      "r2",
      "upload",
      "storage",
      "cloudflare",
      "json",
      "object-storage",
      "s3",
      "presign",
      "download",
      "attachment",
      "content-disposition",
      "v1.3.7",
      "benchmark",
      "performance",
      "timing",
      "crypto",
      "optimization",
      "measurement"
    ],
    "generated": "2026-02-07T05:42:10.412Z",
    "version": "3.8.0-provider-enhanced"
  },
  "patterns": [
    {
      "id": "cookie-variant-a",
      "name": "Cookie A/B Testing - Variant A",
      "category": "cookies",
      "tags": [
        "ab-testing",
        "variant",
        "cookie",
        "ui",
        "admin",
        "http",
        "header"
      ],
      "command": "curl -H \"Cookie: variant=A\" http://localhost:3000",
      "description": "A/B testing UI variants using HTTP cookies",
      "patterns": [
        "curl -H \"Cookie: variant={VARIANT}\" {URL}",
        "fetch(\"{URL}\", {headers: {Cookie: \"variant={VARIANT}\"}})",
        "HTTP header manipulation for A/B testing"
      ],
      "codeBlocks": {
        "type": "curl",
        "template": "curl -H \"Cookie: variant={variant}\" {url}",
        "variables": [
          "variant",
          "url"
        ],
        "providerReferences": [
          {
            "provider": "bun_official",
            "category": "api_reference",
            "urlType": "documentation",
            "documentationUrl": "https://bun.sh/docs/api/fetch",
            "examples": [
              "fetch(url, {headers: {Cookie: \"variant=A\"}})"
            ],
            "relatedPatterns": [
              "fetch-http-headers",
              "http-client-requests"
            ]
          }
        ],
        "documentationLinks": [
          "https://bun.sh/docs/api/fetch#headers",
          "https://developer.mozilla.org/en-US/docs/Web/HTTP/Headers/Cookie"
        ],
        "relatedApis": [
          "fetch",
          "Request",
          "Response"
        ]
      },
      "context": {
        "useCase": "A/B testing UI variants",
        "dependencies": [
          "curl",
          "HTTP server"
        ],
        "complexity": "simple",
        "provider": "bun_official",
        "documentationCategory": "api_reference",
        "relatedProviders": [
          "mdn_web_docs",
          "github"
        ],
        "integrations": [
          "HTTP servers",
          "CDN edge computing",
          "Analytics platforms"
        ],
        "alternatives": [
          "LocalStorage variants",
          "URL parameter testing",
          "Server-side rendering"
        ]
      },
      "performance": {
        "avgTime": 0.02,
        "opsPerSec": 66576,
        "reliability": "high",
        "benchmarks": {
          "bun_official": {
            "opsPerSec": 66576,
            "notes": "Native curl performance"
          },
          "node_js": {
            "opsPerSec": 45231,
            "notes": "Slightly slower HTTP client"
          }
        }
      },
      "providerReferences": [
        {
          "provider": "bun_official",
          "category": "api_reference",
          "urlType": "documentation",
          "domain": "bun.sh",
          "documentationUrl": "https://bun.sh/docs/api/fetch",
          "apiEndpoint": "https://bun.sh/docs/api/fetch#headers"
        },
        {
          "provider": "mdn_web_docs",
          "urlType": "documentation",
          "documentationUrl": "https://developer.mozilla.org/en-US/docs/Web/HTTP/Headers/Cookie"
        }
      ],
      "documentation": {
        "officialDocs": "https://bun.sh/docs/api/fetch",
        "apiReference": "https://bun.sh/docs/api/fetch#headers",
        "examples": [
          "fetch(\"https://api.example.com\", {headers: {Cookie: \"session=abc123\"}})",
          "curl -H \"Cookie: variant=B\" https://app.example.com"
        ],
        "tutorials": [
          "https://bun.sh/guides/http-requests",
          "https://web.dev/cookies"
        ]
      },
      "integrations": {
        "providers": [
          "bun_official",
          "cloudflare",
          "vercel"
        ],
        "apis": [
          "fetch",
          "Request",
          "Response",
          "Headers"
        ],
        "services": [
          "Cloudflare Workers",
          "Vercel Edge Functions",
          "Fastly Compute"
        ]
      }
    },
    {
      "id": "r2-upload-profile",
      "name": "R2 Profile Upload",
      "category": "r2",
      "tags": [
        "r2",
        "upload",
        "storage",
        "cloudflare",
        "json",
        "object-storage"
      ],
      "command": "bun -e 'fetch(\"cf://r2.factory-wager.com/profiles.json\",{method:\"PUT\",body:JSON.stringify({test:1})})'",
      "description": "Object storage upload using Cloudflare R2",
      "patterns": [
        "fetch(\"cf://{bucket}/{path}\",{method:\"PUT\",body:JSON.stringify({data})})",
        "R2 storage operations with cf:// protocol",
        "Cloudflare R2 object upload patterns"
      ],
      "codeBlocks": {
        "type": "r2",
        "template": "fetch(\"cf://{bucket}/{path}\",{method:\"PUT\",body:JSON.stringify({data})})",
        "variables": [
          "bucket",
          "path",
          "data"
        ],
        "providerReferences": [
          {
            "provider": "cloudflare",
            "category": "api_reference",
            "urlType": "documentation",
            "documentationUrl": "https://developers.cloudflare.com/r2/api/workers/workers-api-usage/",
            "examples": [
              "fetch(\"cf://my-bucket/file.txt\", {method: \"PUT\", body: \"content\"})"
            ],
            "relatedPatterns": [
              "r2-download",
              "r2-list-objects",
              "r2-delete"
            ]
          }
        ],
        "documentationLinks": [
          "https://developers.cloudflare.com/r2/",
          "https://bun.sh/docs/runtime/cloudflare-r2"
        ],
        "relatedApis": [
          "fetch",
          "R2Bucket",
          "R2Object"
        ]
      },
      "context": {
        "useCase": "Object storage upload",
        "dependencies": [
          "Bun",
          "Cloudflare R2"
        ],
        "complexity": "intermediate",
        "provider": "cloudflare",
        "documentationCategory": "api_reference",
        "relatedProviders": [
          "bun_official",
          "github"
        ],
        "integrations": [
          "Cloudflare Workers",
          "Serverless applications",
          "CDN edge storage"
        ],
        "alternatives": [
          "AWS S3",
          "Google Cloud Storage",
          "Azure Blob Storage"
        ]
      },
      "performance": {
        "avgTime": 0,
        "opsPerSec": 634840,
        "reliability": "high",
        "benchmarks": {
          "cloudflare": {
            "opsPerSec": 634840,
            "notes": "Direct R2 protocol access"
          },
          "aws_s3": {
            "opsPerSec": 425670,
            "notes": "S3 API via fetch"
          }
        }
      },
      "providerReferences": [
        {
          "provider": "cloudflare",
          "category": "api_reference",
          "urlType": "documentation",
          "documentationUrl": "https://developers.cloudflare.com/r2/api/workers/workers-api-usage/"
        },
        {
          "provider": "bun_official",
          "category": "runtime_features",
          "urlType": "documentation",
          "documentationUrl": "https://bun.sh/docs/runtime/cloudflare-r2"
        }
      ],
      "documentation": {
        "officialDocs": "https://developers.cloudflare.com/r2/",
        "apiReference": "https://developers.cloudflare.com/r2/api/workers/workers-api-usage/",
        "examples": [
          "await env.MY_BUCKET.put(\"file.txt\", \"content\")",
          "fetch(\"cf://bucket/object.json\", {method: \"PUT\", body: JSON.stringify(data)})"
        ],
        "tutorials": [
          "https://developers.cloudflare.com/r2/get-started/",
          "https://bun.sh/guides/r2-storage"
        ]
      },
      "integrations": {
        "providers": [
          "cloudflare",
          "bun_official",
          "github"
        ],
        "apis": [
          "R2Bucket",
          "R2Object",
          "fetch",
          "cf:// protocol"
        ],
        "services": [
          "Cloudflare R2",
          "Cloudflare Workers",
          "Pages Functions"
        ]
      }
    },
    {
      "id": "s3-presign-download",
      "name": "S3 Presigned Download URL",
      "category": "s3-presign",
      "tags": [
        "s3",
        "presign",
        "download",
        "attachment",
        "content-disposition",
        "v1.3.7"
      ],
      "command": "bun -e 'import{S3Client}from\"bun\";const s3=new S3Client({endpoint:\"https://r2.factory-wager.com\",accessKeyId:process.env.R2_ACCESS_KEY_ID,secretAccessKey:process.env.R2_SECRET_ACCESS_KEY,bucket:\"factory-wager-storage\"});console.log(s3.file(\"profile.json\").presign({method:\"GET\",expiresIn:900,contentDisposition:\"attachment; filename=\\\"profile.json\\\"\",type:\"application/json\"}))'",
      "description": "Generate presigned S3 download URLs with content disposition (Bun v1.3.7+)",
      "patterns": [
        "s3.file(\"{key}\").presign({method:\"GET\",contentDisposition:\"{disposition}\",type:\"{contentType}\"})",
        "S3 presign URL generation with v1.3.7 enhancements",
        "Content disposition and type options for downloads"
      ],
      "codeBlocks": {
        "type": "s3",
        "template": "s3.file(\"{key}\").presign({method:\"GET\",expiresIn:900,contentDisposition:\"attachment; filename=\\\"{filename}\\\"\",type:\"{contentType}\"})",
        "variables": [
          "key",
          "filename",
          "contentType"
        ],
        "providerReferences": [
          {
            "provider": "bun_official",
            "category": "api_reference",
            "urlType": "documentation",
            "documentationUrl": "https://bun.sh/docs/api/s3",
            "examples": [
              "s3.file(\"report.pdf\").presign({method: \"GET\", contentDisposition: \"attachment\"})",
              "s3.file(\"image.png\").presign({method: \"GET\", contentDisposition: \"inline\", type: \"image/png\"})"
            ],
            "relatedPatterns": [
              "s3-presign-upload",
              "s3-presign-view",
              "s3-batch-presign"
            ]
          }
        ],
        "documentationLinks": [
          "https://bun.sh/docs/api/s3",
          "https://docs.aws.amazon.com/AmazonS3/latest/userguide/ShareObjectPreSignedURL.html"
        ],
        "relatedApis": [
          "S3Client",
          "S3File",
          "presign"
        ]
      },
      "context": {
        "useCase": "Secure file download URLs",
        "dependencies": [
          "Bun S3Client",
          "AWS S3/R2"
        ],
        "complexity": "advanced",
        "provider": "bun_official",
        "documentationCategory": "api_reference",
        "relatedProviders": [
          "github",
          "cloudflare"
        ],
        "integrations": [
          "Cloud storage services",
          "CDN integration",
          "Secure file sharing"
        ],
        "alternatives": [
          "Cloudflare signed URLs",
          "AWS SDK presign",
          "Custom token-based URLs"
        ]
      },
      "performance": {
        "avgTime": 0.05,
        "opsPerSec": 45000,
        "reliability": "high",
        "benchmarks": {
          "bun_official": {
            "opsPerSec": 45000,
            "notes": "Native S3Client implementation"
          },
          "aws_sdk": {
            "opsPerSec": 32000,
            "notes": "AWS SDK v3 JavaScript"
          }
        }
      },
      "providerReferences": [
        {
          "provider": "bun_official",
          "category": "api_reference",
          "urlType": "documentation",
          "documentationUrl": "https://bun.sh/docs/api/s3"
        }
      ],
      "documentation": {
        "officialDocs": "https://bun.sh/docs/api/s3",
        "apiReference": "https://bun.sh/docs/api/s3#presign",
        "examples": [
          "const url = s3.file(\"document.pdf\").presign({method: \"GET\", expiresIn: 3600})",
          "s3.file(\"image.jpg\").presign({method: \"GET\", contentDisposition: \"inline\", type: \"image/jpeg\"})"
        ],
        "tutorials": [
          "https://bun.sh/guides/s3-storage",
          "https://docs.aws.amazon.com/AmazonS3/latest/userguide/ShareObjectPreSignedURL.html"
        ]
      },
      "integrations": {
        "providers": [
          "bun_official",
          "cloudflare",
          "github"
        ],
        "apis": [
          "S3Client",
          "S3File",
          "presign",
          "contentDisposition"
        ],
        "services": [
          "AWS S3",
          "Cloudflare R2",
          "DigitalOcean Spaces"
        ]
      }
    },
    {
      "id": "performance-benchmark",
      "name": "Performance Benchmark Suite",
      "category": "performance",
      "tags": [
        "benchmark",
        "performance",
        "timing",
        "crypto",
        "optimization",
        "measurement"
      ],
      "command": "bun -e 'const t0=performance.now();for(let i=0;i<100;i++){await new Bun.CryptoHasher(\"sha256\").update(\"test\"+i).digest(\"hex\")}console.log(performance.now()-t0)'",
      "description": "Performance testing and optimization measurement",
      "patterns": [
        "const t0=performance.now();{operations};console.log(performance.now()-t0)",
        "Performance measurement with timing loops",
        "Benchmark suite execution patterns"
      ],
      "codeBlocks": {
        "type": "bun-e",
        "template": "const t0=performance.now();for(let i=0;i<{iterations};i++){{{operations}}}console.log(performance.now()-t0)",
        "variables": [
          "iterations",
          "operations"
        ],
        "providerReferences": [
          {
            "provider": "bun_official",
            "category": "performance_optimization",
            "urlType": "documentation",
            "documentationUrl": "https://bun.sh/docs/performance",
            "examples": [
              "const t0 = performance.now(); // Start timing\nconst result = await someOperation();\nconsole.log(performance.now() - t0); // End timing"
            ],
            "relatedPatterns": [
              "bulk-operations",
              "memory-profiling",
              "throughput-testing"
            ]
          }
        ],
        "documentationLinks": [
          "https://bun.sh/docs/performance",
          "https://web.dev/performance"
        ],
        "relatedApis": [
          "performance.now",
          "CryptoHasher",
          "Bun.gc"
        ]
      },
      "context": {
        "useCase": "Performance testing and optimization",
        "dependencies": [
          "Bun",
          "performance API"
        ],
        "complexity": "intermediate",
        "provider": "bun_official",
        "documentationCategory": "performance_optimization",
        "relatedProviders": [
          "performance_guides",
          "mdn_web_docs"
        ],
        "integrations": [
          "Performance monitoring",
          "Optimization workflows",
          "Benchmarking suites"
        ],
        "alternatives": [
          "Node.js perf_hooks",
          "Browser performance API",
          "Custom timing utilities"
        ]
      },
      "performance": {
        "avgTime": 0.19,
        "opsPerSec": 1432989,
        "reliability": "high",
        "benchmarks": {
          "bun_official": {
            "opsPerSec": 1432989,
            "notes": "Native performance API"
          },
          "node_js": {
            "opsPerSec": 987654,
            "notes": "perf_hooks module"
          }
        }
      },
      "providerReferences": [
        {
          "provider": "bun_official",
          "category": "performance_optimization",
          "urlType": "documentation",
          "documentationUrl": "https://bun.sh/docs/performance"
        },
        {
          "provider": "performance_guides",
          "urlType": "documentation",
          "documentationUrl": "https://web.dev/performance"
        }
      ],
      "documentation": {
        "officialDocs": "https://bun.sh/docs/performance",
        "apiReference": "https://bun.sh/docs/performance#timing",
        "examples": [
          "const start = performance.now();\nawait operation();\nconsole.log(`Operation took ${performance.now() - start}ms`)",
          "for (let i = 0; i < 1000; i++) {\n  const t0 = performance.now();\n  await crypto.hash(data);\n  times.push(performance.now() - t0);\n}"
        ],
        "tutorials": [
          "https://bun.sh/guides/performance-optimization",
          "https://web.dev/fast"
        ]
      },
      "integrations": {
        "providers": [
          "bun_official",
          "performance_guides",
          "mdn_web_docs"
        ],
        "apis": [
          "performance.now",
          "CryptoHasher",
          "Bun.gc",
          "PerformanceObserver"
        ],
        "services": [
          "Performance monitoring platforms",
          "APM tools",
          "Benchmarking services"
        ]
      }
    }
  ],
  "crossReferences": {
    "providerIndex": {
      "bun_official": [
        "cookie-variant-a",
        "cookie-variant-a",
        "r2-upload-profile",
        "r2-upload-profile",
        "s3-presign-download",
        "s3-presign-download",
        "performance-benchmark",
        "performance-benchmark"
      ],
      "mdn_web_docs": [
        "cookie-variant-a",
        "performance-benchmark",
        "performance-benchmark"
      ],
      "github": [
        "cookie-variant-a",
        "r2-upload-profile",
        "r2-upload-profile",
        "s3-presign-download",
        "s3-presign-download"
      ],
      "cloudflare": [
        "cookie-variant-a",
        "r2-upload-profile",
        "r2-upload-profile",
        "s3-presign-download",
        "s3-presign-download"
      ],
      "vercel": [
        "cookie-variant-a"
      ],
      "performance_guides": [
        "performance-benchmark",
        "performance-benchmark"
      ]
    },
    "categoryIndex": {
      "cookies": [
        "cookie-variant-a"
      ],
      "r2": [
        "r2-upload-profile"
      ],
      "s3-presign": [
        "s3-presign-download"
      ],
      "performance": [
        "performance-benchmark"
      ]
    },
    "tagIndex": {
      "ab-testing": [
        "cookie-variant-a"
      ],
      "variant": [
        "cookie-variant-a"
      ],
      "cookie": [
        "cookie-variant-a"
      ],
      "ui": [
        "cookie-variant-a"
      ],
      "admin": [
        "cookie-variant-a"
      ],
      "http": [
        "cookie-variant-a"
      ],
      "header": [
        "cookie-variant-a"
      ],
      "r2": [
        "r2-upload-profile"
      ],
      "upload": [
        "r2-upload-profile"
      ],
      "storage": [
        "r2-upload-profile"
      ],
      "cloudflare": [
        "r2-upload-profile"
      ],
      "json": [
        "r2-upload-profile"
      ],
      "object-storage": [
        "r2-upload-profile"
      ],
      "s3": [
        "s3-presign-download"
      ],
      "presign": [
        "s3-presign-download"
      ],
      "download": [
        "s3-presign-download"
      ],
      "attachment": [
        "s3-presign-download"
      ],
      "content-disposition": [
        "s3-presign-download"
      ],
      "v1.3.7": [
        "s3-presign-download"
      ],
      "benchmark": [
        "performance-benchmark"
      ],
      "performance": [
        "performance-benchmark"
      ],
      "timing": [
        "performance-benchmark"
      ],
      "crypto": [
        "performance-benchmark"
      ],
      "optimization": [
        "performance-benchmark"
      ],
      "measurement": [
        "performance-benchmark"
      ]
    }
  }
}