{
  "timestamp": 1768794873990,
  "duration": 62,
  "tests": [
    {
      "name": "fibonacci-recursive",
      "duration": 38.37116599828005,
      "memoryUsage": 0,
      "operationsPerSecond": 26.061235669638606,
      "metadata": {
        "result": 9227465,
        "iterations": 1
      }
    },
    {
      "name": "array-operations",
      "duration": 0.15770800039172173,
      "memoryUsage": 0,
      "operationsPerSecond": 63408324.08731061,
      "metadata": {
        "result": 74985000,
        "arraySize": 10000
      }
    },
    {
      "name": "string-processing",
      "duration": 0.6637080013751984,
      "memoryUsage": 0,
      "operationsPerSecond": 7533433.361719362,
      "metadata": {
        "resultLength": 173890,
        "iterations": 5000
      }
    },
    {
      "name": "object-creation",
      "duration": 0.9031249992549419,
      "memoryUsage": 0,
      "operationsPerSecond": 5536332.184498147,
      "metadata": {
        "objectCount": 5000,
        "totalObjects": 5000
      }
    },
    {
      "name": "math-operations",
      "duration": 0.5893750004470348,
      "operationsPerSecond": 169671261.8013167,
      "metadata": {
        "result": -44.9014555525699,
        "iterations": 100000
      }
    },
    {
      "name": "json-processing",
      "duration": 0.9457079991698265,
      "memoryUsage": 0,
      "operationsPerSecond": 1057408.841712064,
      "metadata": {
        "jsonSize": 210457,
        "itemCount": 1000
      }
    }
  ],
  "summary": {
    "passed": 6,
    "failed": 0,
    "total": 6,
    "regressions": []
  },
  "environment": {
    "platform": "darwin",
    "arch": "arm64",
    "nodeVersion": "v24.3.0",
    "bunVersion": "1.1.3"
  }
}