{
  "timestamp": 1768821576555,
  "duration": 127,
  "tests": [
    {
      "name": "fibonacci-recursive",
      "duration": 59.92137499898672,
      "memoryUsage": 0,
      "operationsPerSecond": 16.688535602143812,
      "metadata": {
        "result": 9227465,
        "iterations": 1
      }
    },
    {
      "name": "array-operations",
      "duration": 1.8639580011367798,
      "memoryUsage": 0,
      "operationsPerSecond": 5364927.747246053,
      "metadata": {
        "result": 74985000,
        "arraySize": 10000
      }
    },
    {
      "name": "string-processing",
      "duration": 10.46908300369978,
      "memoryUsage": 0,
      "operationsPerSecond": 477596.7482761382,
      "metadata": {
        "resultLength": 173890,
        "iterations": 5000
      }
    },
    {
      "name": "object-creation",
      "duration": 2.386583000421524,
      "memoryUsage": 0,
      "operationsPerSecond": 2095045.5103035963,
      "metadata": {
        "objectCount": 5000,
        "totalObjects": 5000
      }
    },
    {
      "name": "math-operations",
      "duration": 1.5461670011281967,
      "operationsPerSecond": 64676066.63900644,
      "metadata": {
        "result": -44.9014555525699,
        "iterations": 100000
      }
    },
    {
      "name": "json-processing",
      "duration": 1.7609170004725456,
      "memoryUsage": 0,
      "operationsPerSecond": 567885.9365499044,
      "metadata": {
        "jsonSize": 210454,
        "itemCount": 1000
      }
    }
  ],
  "summary": {
    "passed": 6,
    "failed": 0,
    "total": 6,
    "regressions": []
  },
  "environment": {
    "platform": "darwin",
    "arch": "arm64",
    "nodeVersion": "v24.3.0",
    "bunVersion": "1.1.3"
  }
}