{
  "timestamp": 1768795654039,
  "duration": 62,
  "tests": [
    {
      "name": "fibonacci-recursive",
      "duration": 39.529000002890825,
      "memoryUsage": 0,
      "operationsPerSecond": 25.29788256537904,
      "metadata": {
        "result": 9227465,
        "iterations": 1
      }
    },
    {
      "name": "array-operations",
      "duration": 0.34508300200104713,
      "memoryUsage": 0,
      "operationsPerSecond": 28978535.430643015,
      "metadata": {
        "result": 74985000,
        "arraySize": 10000
      }
    },
    {
      "name": "string-processing",
      "duration": 0.7132920026779175,
      "memoryUsage": 0,
      "operationsPerSecond": 7009751.940619638,
      "metadata": {
        "resultLength": 173890,
        "iterations": 5000
      }
    },
    {
      "name": "object-creation",
      "duration": 0.6637500002980232,
      "memoryUsage": 0,
      "operationsPerSecond": 7532956.682116766,
      "metadata": {
        "objectCount": 5000,
        "totalObjects": 5000
      }
    },
    {
      "name": "math-operations",
      "duration": 0.6837499998509884,
      "operationsPerSecond": 146252285.22382933,
      "metadata": {
        "result": -44.9014555525699,
        "iterations": 100000
      }
    },
    {
      "name": "json-processing",
      "duration": 0.9094999991357327,
      "memoryUsage": 0,
      "operationsPerSecond": 1099505.2236946307,
      "metadata": {
        "jsonSize": 210494,
        "itemCount": 1000
      }
    }
  ],
  "summary": {
    "passed": 6,
    "failed": 0,
    "total": 6,
    "regressions": []
  },
  "environment": {
    "platform": "darwin",
    "arch": "arm64",
    "nodeVersion": "v24.3.0",
    "bunVersion": "1.1.3"
  }
}