{
  "timestamp": 1768787853781,
  "duration": 73,
  "tests": [
    {
      "name": "fibonacci-recursive",
      "duration": 43.55250000022352,
      "memoryUsage": 0,
      "operationsPerSecond": 22.960794443369906,
      "metadata": {
        "result": 9227465,
        "iterations": 1
      }
    },
    {
      "name": "array-operations",
      "duration": 0.4139580000191927,
      "memoryUsage": 0,
      "operationsPerSecond": 24157040.085072305,
      "metadata": {
        "result": 74985000,
        "arraySize": 10000
      }
    },
    {
      "name": "string-processing",
      "duration": 0.79691700078547,
      "memoryUsage": 0,
      "operationsPerSecond": 6274179.11159107,
      "metadata": {
        "resultLength": 173890,
        "iterations": 5000
      }
    },
    {
      "name": "object-creation",
      "duration": 2.6475419998168945,
      "memoryUsage": 0,
      "operationsPerSecond": 1888544.1667576202,
      "metadata": {
        "objectCount": 5000,
        "totalObjects": 5000
      }
    },
    {
      "name": "math-operations",
      "duration": 0.7670830003917217,
      "operationsPerSecond": 130363989.227937,
      "metadata": {
        "result": -44.9014555525699,
        "iterations": 100000
      }
    },
    {
      "name": "json-processing",
      "duration": 1.033874999731779,
      "memoryUsage": 0,
      "operationsPerSecond": 967234.9174314425,
      "metadata": {
        "jsonSize": 210559,
        "itemCount": 1000
      }
    }
  ],
  "summary": {
    "passed": 6,
    "failed": 0,
    "total": 6,
    "regressions": [
      "object-creation"
    ]
  },
  "environment": {
    "platform": "darwin",
    "arch": "arm64",
    "nodeVersion": "v24.3.0",
    "bunVersion": "1.1.3"
  }
}