{
  "timestamp": 1768799284651,
  "duration": 219,
  "tests": [
    {
      "name": "fibonacci-recursive",
      "duration": 106.44062500074506,
      "memoryUsage": 0,
      "operationsPerSecond": 9.394909133547461,
      "metadata": {
        "result": 9227465,
        "iterations": 1
      }
    },
    {
      "name": "array-operations",
      "duration": 0.4855410009622574,
      "memoryUsage": 0,
      "operationsPerSecond": 20595583.030437693,
      "metadata": {
        "result": 74985000,
        "arraySize": 10000
      }
    },
    {
      "name": "string-processing",
      "duration": 9.33958300203085,
      "memoryUsage": 0,
      "operationsPerSecond": 535355.8075251082,
      "metadata": {
        "resultLength": 173890,
        "iterations": 5000
      }
    },
    {
      "name": "object-creation",
      "duration": 14.041250001639128,
      "memoryUsage": 0,
      "operationsPerSecond": 356093.6525890727,
      "metadata": {
        "objectCount": 5000,
        "totalObjects": 5000
      }
    },
    {
      "name": "math-operations",
      "duration": 3.4189170002937317,
      "operationsPerSecond": 29249028.27164527,
      "metadata": {
        "result": -44.9014555525699,
        "iterations": 100000
      }
    },
    {
      "name": "json-processing",
      "duration": 8.144040998071432,
      "memoryUsage": 0,
      "operationsPerSecond": 122789.16575159765,
      "metadata": {
        "jsonSize": 210420,
        "itemCount": 1000
      }
    }
  ],
  "summary": {
    "passed": 5,
    "failed": 1,
    "total": 6,
    "regressions": [
      "string-processing",
      "object-creation",
      "math-operations",
      "json-processing"
    ]
  },
  "environment": {
    "platform": "darwin",
    "arch": "arm64",
    "nodeVersion": "v24.3.0",
    "bunVersion": "1.1.3"
  }
}