{
  "timestamp": 1768801354739,
  "duration": 162,
  "tests": [
    {
      "name": "fibonacci-recursive",
      "duration": 106.5190000012517,
      "memoryUsage": 0,
      "operationsPerSecond": 9.387996507554982,
      "metadata": {
        "result": 9227465,
        "iterations": 1
      }
    },
    {
      "name": "array-operations",
      "duration": 0.6256249994039536,
      "memoryUsage": 0,
      "operationsPerSecond": 15984015.9992443,
      "metadata": {
        "result": 74985000,
        "arraySize": 10000
      }
    },
    {
      "name": "string-processing",
      "duration": 2.8791249990463257,
      "memoryUsage": 0,
      "operationsPerSecond": 1736638.7363022405,
      "metadata": {
        "resultLength": 173890,
        "iterations": 5000
      }
    },
    {
      "name": "object-creation",
      "duration": 3.8785420022904873,
      "memoryUsage": 0,
      "operationsPerSecond": 1289144.2188964903,
      "metadata": {
        "objectCount": 5000,
        "totalObjects": 5000
      }
    },
    {
      "name": "math-operations",
      "duration": 1.2992919981479645,
      "operationsPerSecond": 76964993.35218096,
      "metadata": {
        "result": -44.9014555525699,
        "iterations": 100000
      }
    },
    {
      "name": "json-processing",
      "duration": 1.866916999220848,
      "memoryUsage": 0,
      "operationsPerSecond": 535642.4524589721,
      "metadata": {
        "jsonSize": 210550,
        "itemCount": 1000
      }
    }
  ],
  "summary": {
    "passed": 5,
    "failed": 1,
    "total": 6,
    "regressions": []
  },
  "environment": {
    "platform": "darwin",
    "arch": "arm64",
    "nodeVersion": "v24.3.0",
    "bunVersion": "1.1.3"
  }
}