{
  "timestamp": 1768788693803,
  "duration": 73,
  "tests": [
    {
      "name": "fibonacci-recursive",
      "duration": 41.62454100139439,
      "memoryUsage": 0,
      "operationsPerSecond": 24.02428893970268,
      "metadata": {
        "result": 9227465,
        "iterations": 1
      }
    },
    {
      "name": "array-operations",
      "duration": 0.5039589982479811,
      "memoryUsage": 0,
      "operationsPerSecond": 19842884.11312251,
      "metadata": {
        "result": 74985000,
        "arraySize": 10000
      }
    },
    {
      "name": "string-processing",
      "duration": 0.8858750015497208,
      "memoryUsage": 0,
      "operationsPerSecond": 5644137.142659137,
      "metadata": {
        "resultLength": 173890,
        "iterations": 5000
      }
    },
    {
      "name": "object-creation",
      "duration": 1.4720409996807575,
      "memoryUsage": 0,
      "operationsPerSecond": 3396644.5235454403,
      "metadata": {
        "objectCount": 5000,
        "totalObjects": 5000
      }
    },
    {
      "name": "math-operations",
      "duration": 1.19195800088346,
      "operationsPerSecond": 83895573.43956885,
      "metadata": {
        "result": -44.9014555525699,
        "iterations": 100000
      }
    },
    {
      "name": "json-processing",
      "duration": 3.599083000794053,
      "memoryUsage": 0,
      "operationsPerSecond": 277848.5519170782,
      "metadata": {
        "jsonSize": 210579,
        "itemCount": 1000
      }
    }
  ],
  "summary": {
    "passed": 6,
    "failed": 0,
    "total": 6,
    "regressions": []
  },
  "environment": {
    "platform": "darwin",
    "arch": "arm64",
    "nodeVersion": "v24.3.0",
    "bunVersion": "1.1.3"
  }
}