{
  "timestamp": 1768799194719,
  "duration": 185,
  "tests": [
    {
      "name": "fibonacci-recursive",
      "duration": 89.76816700026393,
      "memoryUsage": 0,
      "operationsPerSecond": 11.139806385899135,
      "metadata": {
        "result": 9227465,
        "iterations": 1
      }
    },
    {
      "name": "array-operations",
      "duration": 0.4153750017285347,
      "memoryUsage": 0,
      "operationsPerSecond": 24074631.25702357,
      "metadata": {
        "result": 74985000,
        "arraySize": 10000
      }
    },
    {
      "name": "string-processing",
      "duration": 3.50441699847579,
      "memoryUsage": 0,
      "operationsPerSecond": 1426770.8443871543,
      "metadata": {
        "resultLength": 173890,
        "iterations": 5000
      }
    },
    {
      "name": "object-creation",
      "duration": 23.648042000830173,
      "memoryUsage": 0,
      "operationsPerSecond": 211433.99524681465,
      "metadata": {
        "objectCount": 5000,
        "totalObjects": 5000
      }
    },
    {
      "name": "math-operations",
      "duration": 2.5640839971601963,
      "operationsPerSecond": 39000282.40523834,
      "metadata": {
        "result": -44.9014555525699,
        "iterations": 100000
      }
    },
    {
      "name": "json-processing",
      "duration": 2.5819169990718365,
      "memoryUsage": 0,
      "operationsPerSecond": 387309.1196810301,
      "metadata": {
        "jsonSize": 210441,
        "itemCount": 1000
      }
    }
  ],
  "summary": {
    "passed": 6,
    "failed": 0,
    "total": 6,
    "regressions": [
      "object-creation",
      "math-operations"
    ]
  },
  "environment": {
    "platform": "darwin",
    "arch": "arm64",
    "nodeVersion": "v24.3.0",
    "bunVersion": "1.1.3"
  }
}