{
  "timestamp": 1768849148529,
  "duration": 123,
  "tests": [
    {
      "name": "fibonacci-recursive",
      "duration": 61.71245799958706,
      "memoryUsage": 0,
      "operationsPerSecond": 16.20418360271262,
      "metadata": {
        "result": 9227465,
        "iterations": 1
      }
    },
    {
      "name": "array-operations",
      "duration": 0.20120899379253387,
      "memoryUsage": 0,
      "operationsPerSecond": 49699567.65606103,
      "metadata": {
        "result": 74985000,
        "arraySize": 10000
      }
    },
    {
      "name": "string-processing",
      "duration": 0.9140840023756027,
      "memoryUsage": 0,
      "operationsPerSecond": 5469956.795005225,
      "metadata": {
        "resultLength": 173890,
        "iterations": 5000
      }
    },
    {
      "name": "object-creation",
      "duration": 1.3389589935541153,
      "memoryUsage": 0,
      "operationsPerSecond": 3734244.3077573758,
      "metadata": {
        "objectCount": 5000,
        "totalObjects": 5000
      }
    },
    {
      "name": "math-operations",
      "duration": 0.931207999587059,
      "operationsPerSecond": 107387393.62671353,
      "metadata": {
        "result": -44.9014555525699,
        "iterations": 100000
      }
    },
    {
      "name": "json-processing",
      "duration": 4.975916996598244,
      "memoryUsage": 0,
      "operationsPerSecond": 200967.98252134112,
      "metadata": {
        "jsonSize": 210468,
        "itemCount": 1000
      }
    }
  ],
  "summary": {
    "passed": 6,
    "failed": 0,
    "total": 6,
    "regressions": []
  },
  "environment": {
    "platform": "darwin",
    "arch": "arm64",
    "nodeVersion": "v24.3.0",
    "bunVersion": "1.1.3"
  }
}