{
  "timestamp": 1768815756266,
  "duration": 108,
  "tests": [
    {
      "name": "fibonacci-recursive",
      "duration": 60.015249997377396,
      "memoryUsage": 0,
      "operationsPerSecond": 16.662431632688342,
      "metadata": {
        "result": 9227465,
        "iterations": 1
      }
    },
    {
      "name": "array-operations",
      "duration": 0.3380410000681877,
      "memoryUsage": 0,
      "operationsPerSecond": 29582210.435961485,
      "metadata": {
        "result": 74985000,
        "arraySize": 10000
      }
    },
    {
      "name": "string-processing",
      "duration": 4.445125006139278,
      "memoryUsage": 0,
      "operationsPerSecond": 1124827.7591956062,
      "metadata": {
        "resultLength": 173890,
        "iterations": 5000
      }
    },
    {
      "name": "object-creation",
      "duration": 2.1636250019073486,
      "memoryUsage": 0,
      "operationsPerSecond": 2310936.504982258,
      "metadata": {
        "objectCount": 5000,
        "totalObjects": 5000
      }
    },
    {
      "name": "math-operations",
      "duration": 1.6663330048322678,
      "operationsPerSecond": 60012014.231252626,
      "metadata": {
        "result": -44.9014555525699,
        "iterations": 100000
      }
    },
    {
      "name": "json-processing",
      "duration": 3.9351669996976852,
      "memoryUsage": 0,
      "operationsPerSecond": 254118.82140626403,
      "metadata": {
        "jsonSize": 210584,
        "itemCount": 1000
      }
    }
  ],
  "summary": {
    "passed": 6,
    "failed": 0,
    "total": 6,
    "regressions": []
  },
  "environment": {
    "platform": "darwin",
    "arch": "arm64",
    "nodeVersion": "v24.3.0",
    "bunVersion": "1.1.3"
  }
}