{
  "timestamp": 1768842307621,
  "duration": 112,
  "tests": [
    {
      "name": "fibonacci-recursive",
      "duration": 38.863834008574486,
      "memoryUsage": 0,
      "operationsPerSecond": 25.730863295149188,
      "metadata": {
        "result": 9227465,
        "iterations": 1
      }
    },
    {
      "name": "array-operations",
      "duration": 2.4183329939842224,
      "memoryUsage": 0,
      "operationsPerSecond": 4135079.835934804,
      "metadata": {
        "result": 74985000,
        "arraySize": 10000
      }
    },
    {
      "name": "string-processing",
      "duration": 15.246207997202873,
      "memoryUsage": 0,
      "operationsPerSecond": 327950.39926762896,
      "metadata": {
        "resultLength": 173890,
        "iterations": 5000
      }
    },
    {
      "name": "object-creation",
      "duration": 1.4326250106096268,
      "memoryUsage": 0,
      "operationsPerSecond": 3490096.8243408953,
      "metadata": {
        "objectCount": 5000,
        "totalObjects": 5000
      }
    },
    {
      "name": "math-operations",
      "duration": 2.2975829988718033,
      "operationsPerSecond": 43523998.93675381,
      "metadata": {
        "result": -44.9014555525699,
        "iterations": 100000
      }
    },
    {
      "name": "json-processing",
      "duration": 3.5298749953508377,
      "memoryUsage": 0,
      "operationsPerSecond": 283296.1510866786,
      "metadata": {
        "jsonSize": 210524,
        "itemCount": 1000
      }
    }
  ],
  "summary": {
    "passed": 6,
    "failed": 0,
    "total": 6,
    "regressions": []
  },
  "environment": {
    "platform": "darwin",
    "arch": "arm64",
    "nodeVersion": "v24.3.0",
    "bunVersion": "1.1.3"
  }
}