{
  "timestamp": 1768778883438,
  "duration": 64,
  "tests": [
    {
      "name": "fibonacci-recursive",
      "duration": 38.232665999792516,
      "memoryUsage": 0,
      "operationsPerSecond": 26.15564397223638,
      "metadata": {
        "result": 9227465,
        "iterations": 1
      }
    },
    {
      "name": "array-operations",
      "duration": 0.15058400016278028,
      "memoryUsage": 0,
      "operationsPerSecond": 66408117.65652438,
      "metadata": {
        "result": 74985000,
        "arraySize": 10000
      }
    },
    {
      "name": "string-processing",
      "duration": 3.256792000029236,
      "memoryUsage": 0,
      "operationsPerSecond": 1535253.0956705601,
      "metadata": {
        "resultLength": 173890,
        "iterations": 5000
      }
    },
    {
      "name": "object-creation",
      "duration": 0.790499999653548,
      "memoryUsage": 0,
      "operationsPerSecond": 6325110.692209167,
      "metadata": {
        "objectCount": 5000,
        "totalObjects": 5000
      }
    },
    {
      "name": "math-operations",
      "duration": 0.5691660000011325,
      "operationsPerSecond": 175695666.993111,
      "metadata": {
        "result": -44.9014555525699,
        "iterations": 100000
      }
    },
    {
      "name": "json-processing",
      "duration": 0.8443330000154674,
      "memoryUsage": 0,
      "operationsPerSecond": 1184366.831548312,
      "metadata": {
        "jsonSize": 210464,
        "itemCount": 1000
      }
    }
  ],
  "summary": {
    "passed": 6,
    "failed": 0,
    "total": 6,
    "regressions": [
      "string-processing"
    ]
  },
  "environment": {
    "platform": "darwin",
    "arch": "arm64",
    "nodeVersion": "v24.3.0",
    "bunVersion": "1.1.3"
  }
}