{
  "timestamp": 1768835647132,
  "duration": 106,
  "tests": [
    {
      "name": "fibonacci-recursive",
      "duration": 66.0694160014391,
      "memoryUsage": 0,
      "operationsPerSecond": 15.13559617324631,
      "metadata": {
        "result": 9227465,
        "iterations": 1
      }
    },
    {
      "name": "array-operations",
      "duration": 0.4910829961299896,
      "memoryUsage": 0,
      "operationsPerSecond": 20363156.694093723,
      "metadata": {
        "result": 74985000,
        "arraySize": 10000
      }
    },
    {
      "name": "string-processing",
      "duration": 2.8176669999957085,
      "memoryUsage": 0,
      "operationsPerSecond": 1774517.7127061556,
      "metadata": {
        "resultLength": 173890,
        "iterations": 5000
      }
    },
    {
      "name": "object-creation",
      "duration": 3.8635419979691505,
      "memoryUsage": 0,
      "operationsPerSecond": 1294149.2554314726,
      "metadata": {
        "objectCount": 5000,
        "totalObjects": 5000
      }
    },
    {
      "name": "math-operations",
      "duration": 1.1138330027461052,
      "operationsPerSecond": 89780065.55152747,
      "metadata": {
        "result": -44.9014555525699,
        "iterations": 100000
      }
    },
    {
      "name": "json-processing",
      "duration": 1.7078749984502792,
      "memoryUsage": 0,
      "operationsPerSecond": 585522.9457117161,
      "metadata": {
        "jsonSize": 210456,
        "itemCount": 1000
      }
    }
  ],
  "summary": {
    "passed": 6,
    "failed": 0,
    "total": 6,
    "regressions": []
  },
  "environment": {
    "platform": "darwin",
    "arch": "arm64",
    "nodeVersion": "v24.3.0",
    "bunVersion": "1.1.3"
  }
}