{
  "timestamp": 1768839097292,
  "duration": 88,
  "tests": [
    {
      "name": "fibonacci-recursive",
      "duration": 55.31708300113678,
      "memoryUsage": 0,
      "operationsPerSecond": 18.077598198362153,
      "metadata": {
        "result": 9227465,
        "iterations": 1
      }
    },
    {
      "name": "array-operations",
      "duration": 0.4980420023202896,
      "memoryUsage": 0,
      "operationsPerSecond": 20078627.81334058,
      "metadata": {
        "result": 74985000,
        "arraySize": 10000
      }
    },
    {
      "name": "string-processing",
      "duration": 1.0686660036444664,
      "memoryUsage": 0,
      "operationsPerSecond": 4678730.288928931,
      "metadata": {
        "resultLength": 173890,
        "iterations": 5000
      }
    },
    {
      "name": "object-creation",
      "duration": 1.2816670015454292,
      "memoryUsage": 0,
      "operationsPerSecond": 3901169.3317929064,
      "metadata": {
        "objectCount": 5000,
        "totalObjects": 5000
      }
    },
    {
      "name": "math-operations",
      "duration": 0.889833003282547,
      "operationsPerSecond": 112380637.30060053,
      "metadata": {
        "result": -44.9014555525699,
        "iterations": 100000
      }
    },
    {
      "name": "json-processing",
      "duration": 1.7776670008897781,
      "memoryUsage": 0,
      "operationsPerSecond": 562535.0526839214,
      "metadata": {
        "jsonSize": 210365,
        "itemCount": 1000
      }
    }
  ],
  "summary": {
    "passed": 6,
    "failed": 0,
    "total": 6,
    "regressions": []
  },
  "environment": {
    "platform": "darwin",
    "arch": "arm64",
    "nodeVersion": "v24.3.0",
    "bunVersion": "1.1.3"
  }
}