{
  "timestamp": 1768801804498,
  "duration": 138,
  "tests": [
    {
      "name": "fibonacci-recursive",
      "duration": 78.94516600295901,
      "memoryUsage": 0,
      "operationsPerSecond": 12.667020042272355,
      "metadata": {
        "result": 9227465,
        "iterations": 1
      }
    },
    {
      "name": "array-operations",
      "duration": 0.327334001660347,
      "memoryUsage": 0,
      "operationsPerSecond": 30549835.79242203,
      "metadata": {
        "result": 74985000,
        "arraySize": 10000
      }
    },
    {
      "name": "string-processing",
      "duration": 7.475416999310255,
      "memoryUsage": 0,
      "operationsPerSecond": 668859.0081946388,
      "metadata": {
        "resultLength": 173890,
        "iterations": 5000
      }
    },
    {
      "name": "object-creation",
      "duration": 6.273290999233723,
      "memoryUsage": 0,
      "operationsPerSecond": 797029.8206492806,
      "metadata": {
        "objectCount": 5000,
        "totalObjects": 5000
      }
    },
    {
      "name": "math-operations",
      "duration": 0.8379579968750477,
      "operationsPerSecond": 119337723.81542356,
      "metadata": {
        "result": -44.9014555525699,
        "iterations": 100000
      }
    },
    {
      "name": "json-processing",
      "duration": 3.663958001881838,
      "memoryUsage": 0,
      "operationsPerSecond": 272928.89260367944,
      "metadata": {
        "jsonSize": 210476,
        "itemCount": 1000
      }
    }
  ],
  "summary": {
    "passed": 6,
    "failed": 0,
    "total": 6,
    "regressions": [
      "object-creation"
    ]
  },
  "environment": {
    "platform": "darwin",
    "arch": "arm64",
    "nodeVersion": "v24.3.0",
    "bunVersion": "1.1.3"
  }
}